imagenet_w/__init__.py
imagenet_w/watermark_transform.py
imagenet_w/fonts/SourceHanSerifSC-ExtraLight.otf
imagenet_w-1.0.0.dist-info/LICENSE
imagenet_w-1.0.0.dist-info/METADATA
imagenet_w-1.0.0.dist-info/WHEEL
imagenet_w-1.0.0.dist-info/top_level.txt
imagenet_w-1.0.0.dist-info/zip-safe
imagenet_w-1.0.0.dist-info/RECORD
