Metadata-Version: 2.1
Name: imagenet-w
Version: 1.0.0
Summary: ImageNet-W evaluates the watermark shortcut reliance on ImageNet.
Author: Zhiheng Li
Author-email: zhiheng.li@rochester.edu
License: BSD 3-Clause License
Keywords: imagenet,robustness
Classifier: Programming Language :: Python :: 3
License-File: LICENSE
Requires-Dist: Pillow
Requires-Dist: torchvision
Requires-Dist: torch
